ashlog/cli.py
ashlog/commands/auth.py
ashlog/commands/project.py
common/util.py
ashlog_cli-0.0.1.dist-info/LICENSE
ashlog_cli-0.0.1.dist-info/METADATA
ashlog_cli-0.0.1.dist-info/WHEEL
ashlog_cli-0.0.1.dist-info/entry_points.txt
ashlog_cli-0.0.1.dist-info/top_level.txt
ashlog_cli-0.0.1.dist-info/RECORD
