Metadata-Version: 2.1
Name: ashlog-cli
Version: 0.0.1
Summary: A simple command line interface for AshLog.
Home-page: https://github.com/ashlog-rest/cli
Author: Giulio De Matteis
License: UNKNOWN
Project-URL: Bug Tracker, https://github.com/ashlog-rest/cli/issues
Platform: UNKNOWN
License-File: LICENSE
Requires-Dist: click
Requires-Dist: keyring
Requires-Dist: pyyaml
Requires-Dist: requests
